smallcat/__init__.py
smallcat/catalog.py
smallcat/connections.py
smallcat/path_utils.py
smallcat/py.typed
smallcat/datasets/__init__.py
smallcat/datasets/base_dataset.py
smallcat/datasets/csv_dataset.py
smallcat/datasets/delta_table_dataset.py
smallcat/datasets/excel_dataset.py
smallcat/datasets/parquet_dataset.py
smallcat-0.4.2.dist-info/METADATA
smallcat-0.4.2.dist-info/WHEEL
smallcat-0.4.2.dist-info/entry_points.txt
smallcat-0.4.2.dist-info/licenses/LICENSE
smallcat-0.4.2.dist-info/RECORD
