Metadata-Version: 2.4
Name: smallcat
Version: 0.4.2
Summary: Add your description here
License-File: LICENSE
Classifier: Programming Language :: Python :: 3
Classifier: Programming Language :: Python :: 3 :: Only
Classifier: Programming Language :: Python :: 3.11
Classifier: Programming Language :: Python :: 3.12
Classifier: Programming Language :: Python :: 3.13
Requires-Python: >=3.11
Requires-Dist: deltalake>=0.15
Requires-Dist: duckdb>=1.4.1
Requires-Dist: pandas-stubs>=2.3.2.250926
Requires-Dist: pandas>=2.0
Requires-Dist: pyarrow>=16.0.0
Requires-Dist: pydantic>=2.12.2
Requires-Dist: pytest>=8.4.2
Requires-Dist: pyyaml>=6.0.3
Requires-Dist: types-pyyaml>=6.0.12.20250915
